MANIFEST.in
README.txt
RELEASE-NOTE.txt
setup.cfg
setup.py
./etc/scripts/gmvault
./src/gmv/__init__.py
./src/gmv/blowfish.py
./src/gmv/cmdline_utils.py
./src/gmv/collections_utils.py
./src/gmv/credential_utils.py
./src/gmv/gmv_cmd.py
./src/gmv/gmvault.py
./src/gmv/gmvault_const.py
./src/gmv/gmvault_db.py
./src/gmv/gmvault_export.py
./src/gmv/gmvault_utils.py
./src/gmv/imap_utils.py
./src/gmv/log_utils.py
./src/gmv/mod_imap.py
./src/gmv/progress_test.py
./src/gmv/test_utils.py
./src/gmv/validation_tests.py
./src/gmv/conf/__init__.py
./src/gmv/conf/conf_helper.py
./src/gmv/conf/conf_tests.py
./src/gmv/conf/exceptions.py
./src/gmv/conf/utils/__init__.py
./src/gmv/conf/utils/struct_parser.py
./src/gmv/conf/utils/struct_parser_tests.py
gmvault.egg-info/PKG-INFO
gmvault.egg-info/SOURCES.txt
gmvault.egg-info/dependency_links.txt
gmvault.egg-info/requires.txt
gmvault.egg-info/top_level.txt