Metadata-Version: 1.1
Name: gmvault
Version: 1.8-beta
Summary: Tool to backup and restore your Gmail emails at will. http://www.gmvault.org for more info
Home-page: http://www.gmvault.org
Author: Guillaume Aubert
Author-email: guillaume.aubert@gmail.com
License: AGPLv3
Keywords: gmail,email,backup,gmail backup,imap
Platform: UNKNOWN
Classifier: Programming Language :: Python
Classifier: License :: OSI Approved :: GNU Affero General Public License v3
Classifier: Topic :: Communications :: Email
Classifier: Topic :: Communications :: Email :: Post-Office :: IMAP
